{
    "target": {
        "star": "MU Cam",
        "auid": "000-BCZ-393",
        "ra_hms": "06:25:16.25",
        "dec_dms": "73:34:39.1"
    },
    "chart": {
        "chart_id": "X41941QN",
        "fov_arcmin": 60.0,
        "maglimit": 18.0
    },
    "comparison_stars": [
        {
            "auid": "000-BNS-402",
            "ra": "06:27:47.64",
            "dec": "73:51:05.8",
            "label": "91",
            "bands": [
                {
                    "band": "V",
                    "mag": 9.136,
                    "error": 0.033
                },
                {
                    "band": "B",
                    "mag": 9.52,
                    "error": 0.05
                }
            ],
            "comments": ""
        },
        {
            "auid": "000-BNS-404",
            "ra": "06:24:12.55",
            "dec": "73:54:56.9",
            "label": "96",
            "bands": [
                {
                    "band": "V",
                    "mag": 9.621,
                    "error": 0.036
                },
                {
                    "band": "B",
                    "mag": 10.056,
                    "error": 0.055
                }
            ],
            "comments": ""
        },
        {
            "auid": "000-BNX-434",
            "ra": "06:20:07.92",
            "dec": "73:53:30.2",
            "label": "97",
            "bands": [
                {
                    "band": "V",
                    "mag": 9.686,
                    "error": 0.035
                },
                {
                    "band": "B",
                    "mag": 10.39,
                    "error": 0.056
                }
            ],
            "comments": ""
        },
        {
            "auid": "000-BNS-405",
            "ra": "06:24:19.20",
            "dec": "73:58:09.0",
            "label": "99",
            "bands": [
                {
                    "band": "V",
                    "mag": 9.917,
                    "error": 0.038
                },
                {
                    "band": "B",
                    "mag": 10.425,
                    "error": 0.06
                }
            ],
            "comments": ""
        },
        {
            "auid": "000-BNX-435",
            "ra": "06:22:04.12",
            "dec": "73:57:41.0",
            "label": "111",
            "bands": [
                {
                    "band": "V",
                    "mag": 11.054,
                    "error": 0.073
                },
                {
                    "band": "B",
                    "mag": 11.77,
                    "error": 0.196
                },
                {
                    "band": "Rc",
                    "mag": 10.65,
                    "error": 0.094
                },
                {
                    "band": "Ic",
                    "mag": 10.271,
                    "error": 0.112
                }
            ],
            "comments": ""
        },
        {
            "auid": "000-BFT-944",
            "ra": "06:26:05.20",
            "dec": "73:34:16.0",
            "label": "132",
            "bands": [
                {
                    "band": "V",
                    "mag": 13.219,
                    "error": 0.006
                },
                {
                    "band": "B",
                    "mag": 14.167,
                    "error": 0.012
                },
                {
                    "band": "Rc",
                    "mag": 12.574,
                    "error": 0.092
                },
                {
                    "band": "Ic",
                    "mag": 12.073,
                    "error": 0.106
                }
            ],
            "comments": "Sumner Sequence"
        },
        {
            "auid": "000-BFT-945",
            "ra": "06:25:12.00",
            "dec": "73:32:52.0",
            "label": "135",
            "bands": [
                {
                    "band": "V",
                    "mag": 13.482,
                    "error": 0.006
                },
                {
                    "band": "B",
                    "mag": 14.402,
                    "error": 0.013
                },
                {
                    "band": "Rc",
                    "mag": 12.929,
                    "error": 0.098
                },
                {
                    "band": "Ic",
                    "mag": 12.494,
                    "error": 0.11
                }
            ],
            "comments": "Sumner Sequence"
        },
        {
            "auid": "000-BFT-946",
            "ra": "06:25:51.00",
            "dec": "73:32:59.0",
            "label": "140",
            "bands": [
                {
                    "band": "V",
                    "mag": 13.956,
                    "error": 0.0
                },
                {
                    "band": "B",
                    "mag": 14.637,
                    "error": 0.014
                },
                {
                    "band": "Rc",
                    "mag": 13.408,
                    "error": 0.105
                },
                {
                    "band": "Ic",
                    "mag": 12.972,
                    "error": 0.12
                }
            ],
            "comments": "Sumner Sequence"
        },
        {
            "auid": "000-BKW-434",
            "ra": "06:23:42.48",
            "dec": "73:12:40.3",
            "label": "140",
            "bands": [
                {
                    "band": "V",
                    "mag": 13.988,
                    "error": 0.083
                },
                {
                    "band": "B",
                    "mag": 14.498,
                    "error": 0.191
                },
                {
                    "band": "Rc",
                    "mag": 13.601,
                    "error": 0.094
                },
                {
                    "band": "Ic",
                    "mag": 13.238,
                    "error": 0.105
                }
            ],
            "comments": null
        },
        {
            "auid": "000-BFT-947",
            "ra": "06:25:57.30",
            "dec": "73:34:31.0",
            "label": "145",
            "bands": [
                {
                    "band": "V",
                    "mag": 14.508,
                    "error": 0.005
                },
                {
                    "band": "B",
                    "mag": 15.427,
                    "error": 0.012
                },
                {
                    "band": "Rc",
                    "mag": 13.928,
                    "error": 0.102
                },
                {
                    "band": "Ic",
                    "mag": 13.483,
                    "error": 0.119
                }
            ],
            "comments": "Sumner Sequence"
        },
        {
            "auid": "000-BKW-435",
            "ra": "06:23:09.18",
            "dec": "73:11:56.9",
            "label": "145",
            "bands": [
                {
                    "band": "V",
                    "mag": 14.532,
                    "error": 0.077
                },
                {
                    "band": "B",
                    "mag": 15.148,
                    "error": 0.203
                },
                {
                    "band": "Rc",
                    "mag": 14.123,
                    "error": 0.098
                },
                {
                    "band": "Ic",
                    "mag": 13.74,
                    "error": 0.116
                }
            ],
            "comments": null
        },
        {
            "auid": "000-BFT-948",
            "ra": "06:25:20.90",
            "dec": "73:35:48.0",
            "label": "148",
            "bands": [
                {
                    "band": "V",
                    "mag": 14.77,
                    "error": 0.0
                },
                {
                    "band": "B",
                    "mag": 15.509,
                    "error": 0.013
                },
                {
                    "band": "Rc",
                    "mag": 14.26,
                    "error": 0.11
                },
                {
                    "band": "Ic",
                    "mag": 13.877,
                    "error": 0.133
                }
            ],
            "comments": "Sumner Sequence"
        },
        {
            "auid": "000-BKW-436",
            "ra": "06:22:44.67",
            "dec": "73:09:50.0",
            "label": "148",
            "bands": [
                {
                    "band": "V",
                    "mag": 14.806,
                    "error": 0.095
                },
                {
                    "band": "B",
                    "mag": 15.459,
                    "error": 0.207
                },
                {
                    "band": "Rc",
                    "mag": 14.363,
                    "error": 0.113
                },
                {
                    "band": "Ic",
                    "mag": 13.948,
                    "error": 0.129
                }
            ],
            "comments": null
        },
        {
            "auid": "000-BFT-949",
            "ra": "06:25:11.70",
            "dec": "73:33:57.0",
            "label": "153",
            "bands": [
                {
                    "band": "V",
                    "mag": 15.292,
                    "error": 0.006
                },
                {
                    "band": "B",
                    "mag": 15.884,
                    "error": 0.013
                },
                {
                    "band": "Rc",
                    "mag": 14.855,
                    "error": 0.105
                },
                {
                    "band": "Ic",
                    "mag": 14.526,
                    "error": 0.127
                }
            ],
            "comments": "Sumner Sequence"
        },
        {
            "auid": "000-BKW-437",
            "ra": "06:24:19.30",
            "dec": "73:10:01.9",
            "label": "153",
            "bands": [
                {
                    "band": "V",
                    "mag": 15.26,
                    "error": 0.084
                },
                {
                    "band": "B",
                    "mag": 15.828,
                    "error": 0.197
                },
                {
                    "band": "Rc",
                    "mag": 14.882,
                    "error": 0.112
                },
                {
                    "band": "Ic",
                    "mag": 14.527,
                    "error": 0.134
                }
            ],
            "comments": null
        },
        {
            "auid": "000-BKW-438",
            "ra": "06:23:30.28",
            "dec": "73:09:58.3",
            "label": "158",
            "bands": [
                {
                    "band": "V",
                    "mag": 15.811,
                    "error": 0.081
                },
                {
                    "band": "B",
                    "mag": 16.404,
                    "error": 0.196
                },
                {
                    "band": "Rc",
                    "mag": 15.438,
                    "error": 0.108
                },
                {
                    "band": "Ic",
                    "mag": 15.088,
                    "error": 0.13
                }
            ],
            "comments": null
        },
        {
            "auid": "000-BFT-950",
            "ra": "06:25:53.50",
            "dec": "73:32:01.0",
            "label": "161",
            "bands": [
                {
                    "band": "V",
                    "mag": 16.109,
                    "error": 0.006
                },
                {
                    "band": "B",
                    "mag": 17.015,
                    "error": 0.014
                },
                {
                    "band": "Rc",
                    "mag": 15.506,
                    "error": 0.116
                },
                {
                    "band": "Ic",
                    "mag": 15.029,
                    "error": 0.151
                }
            ],
            "comments": "Sumner Sequence"
        },
        {
            "auid": "000-BKW-439",
            "ra": "06:23:18.58",
            "dec": "73:14:45.6",
            "label": "162",
            "bands": [
                {
                    "band": "V",
                    "mag": 16.248,
                    "error": 0.086
                },
                {
                    "band": "B",
                    "mag": 17.098,
                    "error": 0.201
                },
                {
                    "band": "Rc",
                    "mag": 15.674,
                    "error": 0.196
                },
                {
                    "band": "Ic",
                    "mag": 15.139,
                    "error": 0.263
                }
            ],
            "comments": null
        },
        {
            "auid": "000-BKW-440",
            "ra": "06:23:51.28",
            "dec": "73:06:15.4",
            "label": "167",
            "bands": [
                {
                    "band": "V",
                    "mag": 16.671,
                    "error": 0.063
                },
                {
                    "band": "B",
                    "mag": 17.372,
                    "error": 0.143
                },
                {
                    "band": "Rc",
                    "mag": 16.203,
                    "error": 0.117
                },
                {
                    "band": "Ic",
                    "mag": 15.766,
                    "error": 0.152
                }
            ],
            "comments": null
        }
    ]
}