[
  {
    "auid": "000-BMS-438",
    "ra": "19:31:02.83",
    "dec": "23:32:03.8",
    "label": "112",
    "v_mag": 11.154
  },
  {
    "auid": "000-BLB-980",
    "ra": "19:33:05.37",
    "dec": "23:38:00.7",
    "label": "115",
    "v_mag": 11.536
  },
  {
    "auid": "000-BMS-439",
    "ra": "19:31:33.55",
    "dec": "23:28:45.3",
    "label": "119",
    "v_mag": 11.937
  },
  {
    "auid": "000-BMS-440",
    "ra": "19:30:42.96",
    "dec": "23:24:38.4",
    "label": "123",
    "v_mag": 12.328
  },
  {
    "auid": "000-BMS-441",
    "ra": "19:30:04.20",
    "dec": "23:39:05.8",
    "label": "127",
    "v_mag": 12.703
  },
  {
    "auid": "000-BMS-442",
    "ra": "19:31:16.28",
    "dec": "23:30:35.5",
    "label": "131",
    "v_mag": 13.104
  },
  {
    "auid": "000-BMS-443",
    "ra": "19:30:32.23",
    "dec": "23:34:30.6",
    "label": "133",
    "v_mag": 13.261
  },
  {
    "auid": "000-BMS-444",
    "ra": "19:31:33.21",
    "dec": "23:33:33.6",
    "label": "137",
    "v_mag": 13.661
  }
]